my_palette/__init__.py
my_palette/__main__.py
my_palette/_version.py
my_palette/download.jpg
my_palette/functions.py
my_palette/tests/test_all.py
get_my_palette_from_image-0.1.3.dist-info/LICENSE
get_my_palette_from_image-0.1.3.dist-info/METADATA
get_my_palette_from_image-0.1.3.dist-info/WHEEL
get_my_palette_from_image-0.1.3.dist-info/top_level.txt
get_my_palette_from_image-0.1.3.dist-info/RECORD
