Metadata-Version: 2.1
Name: get-my-palette-from-image
Version: 0.1.3
Summary: get-my-palette-from-image is a python library for extracting and manipulating palettes from images
Author-email: Yaochen Shen <ys3593@columbia.edu>
License: Apache License
Project-URL: repository, https://github.com/ys3593/get-my-palette-from-image
Classifier: Development Status :: 2 - Pre-Alpha
Classifier: Programming Language :: Python :: Implementation :: CPython
Classifier: Programming Language :: Python :: Implementation :: PyPy
Classifier: Programming Language :: Python :: 3
Classifier: Programming Language :: Python :: 3.7
Classifier: Programming Language :: Python :: 3.8
Classifier: Programming Language :: Python :: 3.9
Classifier: Programming Language :: Python :: 3.10
Classifier: Programming Language :: Python :: 3.11
Requires-Python: >=3.7
License-File: LICENSE
Requires-Dist: seaborn
Requires-Dist: setuptools
Requires-Dist: numpy
Requires-Dist: opencv-python
Requires-Dist: Pillow
Requires-Dist: matplotlib
Requires-Dist: scikit-learn
Requires-Dist: pytest
Requires-Dist: scipy
Provides-Extra: develop
Requires-Dist: black (>=22) ; extra == 'develop'
Requires-Dist: bump2version (>=1.0.0) ; extra == 'develop'
Requires-Dist: check-manifest ; extra == 'develop'
Requires-Dist: flake8 (>=3.7.8) ; extra == 'develop'
Requires-Dist: flake8-black (>=0.2.1) ; extra == 'develop'
Requires-Dist: flake8-pyproject ; extra == 'develop'
Requires-Dist: mypy ; extra == 'develop'
Requires-Dist: pytest (>=4.3.0) ; extra == 'develop'
Requires-Dist: pytest-cov (>=2.6.1) ; extra == 'develop'
Requires-Dist: twine ; extra == 'develop'
Requires-Dist: wheel ; extra == 'develop'
Requires-Dist: codecov ; extra == 'develop'
